odoo/addons/shopinvader_pending_cart_reminder/README.rst
odoo/addons/shopinvader_pending_cart_reminder/__init__.py
odoo/addons/shopinvader_pending_cart_reminder/__manifest__.py
odoo/addons/shopinvader_pending_cart_reminder/data/ir_cron.xml
odoo/addons/shopinvader_pending_cart_reminder/data/mail_template.xml
odoo/addons/shopinvader_pending_cart_reminder/i18n/shopinvader_pending_cart_reminder.pot
odoo/addons/shopinvader_pending_cart_reminder/models/__init__.py
odoo/addons/shopinvader_pending_cart_reminder/models/sale_order.py
odoo/addons/shopinvader_pending_cart_reminder/models/shopinvader_backend.py
odoo/addons/shopinvader_pending_cart_reminder/readme/CONTRIBUTORS.rst
odoo/addons/shopinvader_pending_cart_reminder/readme/DESCRIPTION.rst
odoo/addons/shopinvader_pending_cart_reminder/readme/USAGE.rst
odoo/addons/shopinvader_pending_cart_reminder/static/description/index.html
odoo/addons/shopinvader_pending_cart_reminder/tests/__init__.py
odoo/addons/shopinvader_pending_cart_reminder/tests/test_sale_order.py
odoo/addons/shopinvader_pending_cart_reminder/tests/test_shopinvader_backend.py
odoo/addons/shopinvader_pending_cart_reminder/views/shopinvader_backend.xml
odoo14_addon_shopinvader_pending_cart_reminder-14.0.1.0.1.dist-info/METADATA
odoo14_addon_shopinvader_pending_cart_reminder-14.0.1.0.1.dist-info/WHEEL
odoo14_addon_shopinvader_pending_cart_reminder-14.0.1.0.1.dist-info/top_level.txt
odoo14_addon_shopinvader_pending_cart_reminder-14.0.1.0.1.dist-info/RECORD
