Metadata-Version: 2.1
Name: odoo14-addon-shopinvader-pending-cart-reminder
Version: 14.0.1.0.1
Summary: Shopinvader module to relaunch the customer when the cart/sale is not confirmed yet. Configure the delay and the email template on the backend.
Home-page: https://github.com/shopinvader/odoo-shopinvader
Author: ACSONE SA/NV
License: AGPL-3
Platform: UNKNOWN
Classifier: Programming Language :: Python
Classifier: Framework :: Odoo
Classifier: Framework :: Odoo :: 14.0
Classifier: License :: OSI Approved :: GNU Affero General Public License v3
Requires-Python: >=3.6
Requires-Dist: odoo14-addon-shopinvader
Requires-Dist: odoo (<14.1dev,>=14.0a)
